{
  "video_title": "【3Dライブ/コラボ】みずしー × ハノン = #ハノしー【#水科葵 #香鳴ハノン】",
  "video_artist": "Hanon Ch. 香鳴ハノン【パレプロ】",
  "video_id": "-aUguqAq2Fs",
  "video_publish_date_str": "2021-10-27 18:11:46",
  "song_timeline": "ハノしー最高でした…！！\n幸せな時間をありがとう！！\n\n0:56 1.だから僕は音楽を辞めた / ヨルシカ#{=香鳴ハノン,水科葵}\n5:10 2.夜に駆ける / YOASOBI#{=水科葵}\n9:43 3.秒針を噛む / ずっと真夜中でいいのに。#{=香鳴ハノン}\n13:58 ～MC①～\n21:10 4.残酷な天使のテーゼ / 高橋洋子#{=水科葵}\n25:33 5.Listen!! / 放課後ティータイム#{=香鳴ハノン}\n29:16 ～MC②～\n37:44 6.瞬間センチメンタル / SCANDAL#{=香鳴ハノン,水科葵}\n41:36 7.chAngE / miwa#{=香鳴ハノン,水科葵}\n48:17 8.Rising Hope/ LiSA#{=香鳴ハノン,水科葵}\n52:26 ～MC③～\n55:17 9.だから僕は音楽を辞めた / ヨルシカ#{=香鳴ハノン,水科葵,アンコール}\n59:22 ～MC④＆スパチャ読み＆宣伝～"
}