{
  "video_title": "【歌枠 / 初見大歓迎】少しだけ聴いていきませんか？きっと癒される歌枠💠【#パレプロ #香鳴ハノン】",
  "video_artist": "Hanon Ch. 香鳴ハノン【パレプロ】",
  "video_id": "nM75jptKa4A",
  "video_publish_date_str": "2022-11-17",
  "song_timeline": "今回のタイムスタンプ＆セトリ\r\n\r\n0:00 待機\r\n2:34 開始 はのは～\r\n\r\n7:52 CHE.R.RY / Yui ~11:22 \r\n13:27 空も飛べるはず / スピッツ ~17:54 \r\n21:04 助かる\r\n23:44 ガーネット / 奥華子 ~28:56 \r\n32:43 花に亡霊 / ヨルシカ ~36:50 \r\n39:33 世界には愛しかない / 櫻坂46 ~44:26\r\n47:09 愛のうた / ストロベリー・フラワー ~50:14 \r\n50:19 愛のうた替え歌(僕たちハノモニ\r\n58:58 ハッピー・ジャムジャム / しまじろう ~1:00:24 \r\n\r\n1:03:00 パプリカ / Foorin ~1:06:16 \r\n1:10:15 ハルカ / YOASOBI ~1:14:21 \r\n\r\n1:18:09 スクショタイム(開始時ミュート)、スパチャ読み、告知\r\n1:34:29 エンドカード\r\n\r\n癒やされる()歌枠お疲れ様でしたー\r\nお陰様でゆっくり寝られそうです\r\n明日のるきあちゃんとのコラボ枠も楽しみにしてますね"
}