{
  "video_title": "【歌枠｜KARAOKE】ボカロ歌枠！✨高音中心だけどがんばるぞ～！【#パレプロ #香鳴ハノン】",
  "video_artist": "Hanon Ch. 香鳴ハノン【パレプロ】",
  "video_id": "wcDOtq5wRck",
  "video_publish_date_str": "2024-11-04",
  "song_timeline": "Today's Set List\r\n0:00:00 OP\r\n0:03:11 はのは～\r\n\r\n0:05:17；0:08:12 グッバイ宣言 / Chinozo\r\n0:09:56；0:12:21 KING / Kanaria\r\n0:14:04；0:17:16 ヴァンパイア / DECO*27\r\n0:23:38；0:27:02 神っぽいな / ピノキオピー\r\n0:29:14；0:33:06 シャルル / バルーンP\r\n0:38:43；0:42:23 メランコリック / Junky feat. 鏡音リン\r\n0:44:18；0:46:36 酔いどれ知らず / Kanaria\r\n0:48:31；0:53:22 少女レイ / みきとP\r\n0:56:06；0:59:24 フォニイ / ツミキ\r\n1:01:39；1:05:43 千本桜 / 黒うさP\r\n1:10:03；1:12:26 強風オールバック / ゆこぴ\r\n\r\n1:13:02 スパチャ読み\r\n1:15:21 エンドカード 11月衣装生写真紹介"
}