{
  "video_title": "【歌枠｜KARAOKE】アニソン縛り✨158曲からみんなに選ばれた名曲たち🎤💞1曲聴いていきませんか？【#パレプロ #香鳴ハノン】",
  "video_artist": "Hanon Ch. 香鳴ハノン【パレプロ】",
  "video_id": "rRuOrlbk30I",
  "video_publish_date_str": "2025-05-14",
  "song_timeline": "0:02:20 はのは〜！\n\n0:06:50 01. 深愛 / 水樹奈々\n0:18:51 02. 深愛 / 水樹奈々\n0:26:42 03. イデア / 天野月子\n0:36:35 04. 1&sol;3の純情な感情 / SIAM SHADE\n0:42:23 05. again / YUI\n\n0:48:16 06. Overfly / 春奈るな\n0:54:23 07. trust you / 伊藤由奈\n1:00:28 08. YUME日和 / 島谷ひとみ\n1:10:56 09. 季節がいく時 / SPEED\n1:17:04 10. 渡月橋 ～君 想ふ～ / 倉木麻衣\n\n1:25:49 11. irony / ClariS\n1:32:00 12. Baby Sweet Berry Love / 小倉唯\n1:39:37 13. ヒトリゴト / ClariS\n1:46:23 14. リテラチュア / 上田麗奈\n1:53:01 15. Be My Friend / 隣人部\n\n1:58:18 16. 残念系隣人部★★☆(星二つ半) / 友達つくり隊\n2:06:58 17. アナタボシ / MilkyWay\n2:11:58 18. ドキピポ☆エモーション / 天王寺璃奈(田中ちえ美)\n2:19:25 19. それは僕たちの奇跡 / μ's\n2:26:32 20. もぎゅっと“love”で接近中! / μ's\n\n2:33:06 21. 夏色えがおで1, 2, Jump! / μ's\n2:39:40 22. 光るなら / Goose house\n\n2:46:55 スパチャ読み\n3:02:56 はのは〜！\n3:04:02 END / Cパート"
}