{
  "video_title": "【重大なお知らせと歌枠/singing stream】心して聞いてください。【 #暁月クララ / #パレプロ / #Vtuber 】",
  "video_artist": "暁月クララ / Akatsuki Clara【パレプロ】",
  "video_id": "4ACT249M6Qo",
  "video_publish_date_str": "2022-02-18 21:12:10",
  "song_timeline": "前半：茶番（告知）\r\n34:21 夢をかなえてドラえもん / mao\r\n48:36 さくらんぼ / 大塚愛\r\n1:06:07 チェリー / スピッツ\r\n1:22:37 ムーンライト伝説 / DALI\r\n1:29:45 ギラギラ / Ado\r\n1:38:29 生まれてはじめて / 神田沙也加・松たか子\r\n1:46:11 KING / Kanaria\r\n1:52:16 ハム太郎とっとこうた / ハムちゃんず\r\n\r\nエンドレスらすとソングとても笑った。\r\nいろいろなお歌きけて私としては嬉しかったですｗ\r\n\r\nお知らせもワクワクな奴でうれしい！　色々楽しみにしています。"
}