{
  "video_title": "【歌枠/singing stream】水着初お披露目👙夏曲で盛り上がろ！！【#クララとおうちで納涼祭り #暁月クララ #パレプロ 】",
  "video_artist": "暁月クララ / Akatsuki Clara【パレプロ】",
  "video_id": "Zdy4dz9mVLw",
  "video_publish_date_str": "2022-08-13 14:15:02",
  "song_timeline": "8:42　　 君と夏フェス/SHISHAMO\n16:14　　夏祭り/Whiteberry\n24:17　　打上花火/DAOKO×米津玄師\n32:29　　ウイスキーが、お好きでしょ/石川さゆり\n\n38:39　　少年時代/井上陽水\n46:28　　残響散歌/Aimer\n53:43　　君の知らない物語/Supercell\n1:11:54　secret base 〜君がくれたもの〜/ZONE\n\nいろんなくーちゃんの夏歌が聞けて楽しかったです。水着すごく可愛い！\n残響散歌すごくかっこよくて良かったです！"
}