{
  "video_title": "✧︎*.姫熊りぼん×暁月クララ┊︎歌唱コラボあり！お歌DEトーク🌟そんなエピソード、ある！？⋆꙳〖#パレプロ〗",
  "video_artist": "暁月クララ / Akatsuki Clara【パレプロ】",
  "video_id": "Pymclh7vJQk",
  "video_publish_date_str": "2023-09-11 22:18:30",
  "song_timeline": "＜セトリ＆トークテーマ＞\n00:00:53　オープニング\n\n00:04:15　ゾンビに襲われたことは？\n00:09:02　中毒になるくらいハマったこと\n\n00:19:29　ちゅ、多様性。/ano\n\n00:24:36　過去の失敗を活かした話\n\n00:35:31　残響散歌/Aimer\n\n00:39:35　テーマパークへ行った話\n00:45:06　ファンの人と笑顔はじける話\n\n00:52:43　Girls★go-round/姫熊りぼん、暁月クララ \n\nセトリの歌詞に合わせたトークテーマとても楽しかったです！\n二人のGirls★go-roundが聞けてとっても嬉しかったです！"
}