{
  "video_title": "✧︎*.歌枠/初見さん歓迎┊︎kawaii♡は世界を救う⋆꙳〖#暁月クララ┊︎#パレプロ〗",
  "video_artist": "暁月クララ / Akatsuki Clara【パレプロ】",
  "video_id": "7qXNvParD3c",
  "video_publish_date_str": "2023-08-20 10:07:23",
  "song_timeline": "＜セトリ＞\n00:04:02　ヘビーローテーション/AKB48\n00:19:48　アンパンマンのマーチ/ドリーミング\n00:22:45　アイドル/YOASOBI\n\n00:32:02　チョコレイト・ディスコ/Perfume　#{=西郷どん？Ver.}\n00:35:50　Tell Your World/livetune\n00:40:07　シル・ヴ・プレジデント/P丸様。\n\n00:48:17　CHE.R.RY/YUI \n00:51:47　ムーンライト伝説/DALI\n00:54:37　チェリー/スピッツ\n\n01:00:37　チェリボム/SILENT SIREN\n01:04:39　可愛くてごめん/HoneyWorks\n\n01:11:26　強風オールバック/Yukopi\n01:17:43　うまぴょい伝説\n\n01:23:57　スパチャ読み&雑談\n\nいろんなかわいい曲を聴けました！\n謎のごわす語尾や強風オールバックのセルフくちリコーダーも好きですｗ"
}