{
  "video_title": "✧︎*.雛森アンシア×暁月クララ┊︎コラボ歌枠で ”かわいい” に溺れたい方募集です💗#アンシアクララ⋆꙳〖#雛森アンシア #暁月クララ┊︎#パレプロ〗",
  "video_artist": "暁月クララ / Akatsuki Clara【パレプロ】",
  "video_id": "YsrAuqv1xXI",
  "video_publish_date_str": "2024-06-18 09:22:17",
  "song_timeline": "＜セトリ＞\n0:03:29　ルージュの伝言/松任谷由実\n0:11:53　サインはB/B小町アイ(高橋李依) \n0:20:32　コネクト/ClariS\n\n0:32:26　だいしきゅーだいしゅき/femme fatale\n0:40:47　Wishing/レム (水瀬いのり) \n0:50:39　ふわふわ時間/放課後ティータイム\n1:03:51　奏/スキマスイッチ\n\n2人のかわいさやせつなさがいっぱい詰まった歌声とっても良かったです！\nハモリや掛け合いも楽しくて、意外な共通点もありとっても楽しかったです！"
}