{
  "video_title": "✧︎*.〖 #サンリオ楽曲歌枠リレー 〗あの感動を少しでも私も届けられますように✨KAWAIIプリンボイスでお送りします💗⋆꙳〖#暁月クララ┊︎#パレプロ〗",
  "video_artist": "暁月クララ / Akatsuki Clara【パレプロ】",
  "video_id": "zS4_yJe4byM",
  "video_publish_date_str": "2025-07-26",
  "song_timeline": "@tomfukuとむふく\n＜セトリ＞\n11:09 KAWAII FESTIVAL/みんななかよく\n18:30 ダイジョーブ/はぴだんぶい\n26:26 Like A Night Cruising/Sputrip\n31:05 みんなでコネクト(Nakayoku Connect)/サンリオピューロランド【公式】\n\n＜おまけ＞\n00:48 開始\n02:48 たるとちゃんとの急遽の雑談コラボ\n\nKAWAII FESTIVALとってもかわいい！\nサンリオさんのキャラクターの思いが聞けて良かったです\nトラブル対応もさすがでした！"
}